gateway_api/__init__.py
gateway_api/gateway_api.py
gateway_api-4.1.dist-info/METADATA
gateway_api-4.1.dist-info/WHEEL
gateway_api-4.1.dist-info/top_level.txt
gateway_api-4.1.dist-info/RECORD
